casageo/tools/__init__.py
casageo/tools/_client.py
casageo/tools/_coder.py
casageo/tools/_consts.py
casageo/tools/_errors.py
casageo/tools/_spatial.py
casageo/tools/_types.py
casageo/tools/_util.py
casageo/tools/_apiclient/geocoder/__init__.py
casageo/tools/_apiclient/geocoder/client.py
casageo/tools/_apiclient/geocoder/errors.py
casageo/tools/_apiclient/geocoder/types.py
casageo/tools/_apiclient/geocoder/api/__init__.py
casageo/tools/_apiclient/geocoder/api/default/__init__.py
casageo/tools/_apiclient/geocoder/api/default/get_autocomplete.py
casageo/tools/_apiclient/geocoder/api/default/get_autosuggest.py
casageo/tools/_apiclient/geocoder/api/default/get_browse.py
casageo/tools/_apiclient/geocoder/api/default/get_discover.py
casageo/tools/_apiclient/geocoder/api/default/get_geocode.py
casageo/tools/_apiclient/geocoder/api/default/get_lookup.py
casageo/tools/_apiclient/geocoder/api/default/get_revgeocode.py
casageo/tools/_apiclient/geocoder/api/default/post_autosuggest.py
casageo/tools/_apiclient/geocoder/api/default/post_browse.py
casageo/tools/_apiclient/geocoder/api/default/post_discover.py
casageo/tools/_apiclient/geocoder/api/default/post_multi_revgeocode.py
casageo/tools/_apiclient/geocoder/models/__init__.py
casageo/tools/_apiclient/geocoder/models/access.py
casageo/tools/_apiclient/geocoder/models/access_restriction_attributes.py
casageo/tools/_apiclient/geocoder/models/address.py
casageo/tools/_apiclient/geocoder/models/address_highlighting_information.py
casageo/tools/_apiclient/geocoder/models/address_usage.py
casageo/tools/_apiclient/geocoder/models/address_usage_usage_type.py
casageo/tools/_apiclient/geocoder/models/admin_id_section.py
casageo/tools/_apiclient/geocoder/models/admin_names.py
casageo/tools/_apiclient/geocoder/models/admin_names_preference.py
casageo/tools/_apiclient/geocoder/models/autocomplete_result_item.py
casageo/tools/_apiclient/geocoder/models/autocomplete_result_item_administrative_area_type.py
casageotools-0.9.0.dist-info/licenses/LICENSE
casageotools-0.9.0.dist-info/METADATA
casageotools-0.9.0.dist-info/WHEEL
casageotools-0.9.0.dist-info/entry_points.txt
casageotools-0.9.0.dist-info/top_level.txt
casageotools-0.9.0.dist-info/RECORD
