Metadata-Version: 2.4
Name: casaGeoTools
Version: 0.9.0
Summary: HERE Connector for Python
Author-email: casaGeo Data + Services GmbH <info@casageo.de>
License-Expression: Apache-2.0
Project-URL: Homepage, https://www.casageo.de/en/here-connector-for-python.html
Project-URL: Source, https://github.com/casaGeo-Data-Services-GmbH/casaGeoTools
Project-URL: Issues, https://github.com/casaGeo-Data-Services-GmbH/casaGeoTools/issues
Classifier: Development Status :: 4 - Beta
Classifier: Environment :: Console
Classifier: Environment :: Web Environment
Classifier: Intended Audience :: Science/Research
Classifier: Operating System :: OS Independent
Classifier: Programming Language :: Python :: 3.13
Classifier: Topic :: Scientific/Engineering :: GIS
Requires-Python: >=3.11
License-File: LICENSE
Requires-Dist: attrs>=25.3.0
Requires-Dist: flexpolyline>=0.1.0
Requires-Dist: geopandas>=1.1.0
Requires-Dist: httpx>=0.28.1
Requires-Dist: pandas>=2.3.0
Dynamic: license-file
